xmlproxy/__init__.py
xmlproxy-0.3.0.dist-info/LICENSE
xmlproxy-0.3.0.dist-info/METADATA
xmlproxy-0.3.0.dist-info/WHEEL
xmlproxy-0.3.0.dist-info/top_level.txt
xmlproxy-0.3.0.dist-info/RECORD
