Metadata-Version: 2.1
Name: xmlproxy
Version: 0.3.0
Summary: UNKNOWN
Home-page: https://github.com/Cologler/xmlproxy-python
License: MIT License
Keywords: xml
Platform: UNKNOWN
Classifier: License :: OSI Approved :: MIT License
Classifier: Programming Language :: Python :: 3.6
Classifier: Programming Language :: Python :: 3.7
Classifier: Programming Language :: Python :: 3.8
